smash/__init__.py
smash_cli-0.2.0.dist-info/licenses/LICENSE
smash_core/__init__.py
smash_core/cli.py
smash_core/context_loader.py
smash_core/files.py
smash_core/helpers.py
smash_core/log.py
smash_core/project.py
smash_core/smashlets.py
smash_cli-0.2.0.dist-info/METADATA
smash_cli-0.2.0.dist-info/WHEEL
smash_cli-0.2.0.dist-info/entry_points.txt
smash_cli-0.2.0.dist-info/top_level.txt
smash_cli-0.2.0.dist-info/RECORD
