Metadata-Version: 2.4
Name: smash-cli
Version: 0.2.0
Summary: A lightweight build system for content
Author-email: Oskar Nyqvist <oskar@example.com>
License-Expression: MIT
Requires-Python: >=3.8
License-File: LICENSE
Dynamic: license-file
